{
  "pagination": {},
  "data": [
    {
      "id": "1946806015980031235_31044967",
      "user": {
        "id": "31044967",
        "full_name": "Ramon",
        "profile_picture": "https://scontent.cdninstagram.com/vp/67c443456e0b9a1e8c4e86177a82ee67/5CDE2DBC/t51.2885-19/s150x150/25038116_1902832036711656_8761951227660468224_n.jpg?_nc_ht=scontent.cdninstagram.com",
        "username": "freecates"
      },
      "images": {
        "thumbnail": {
          "width": 150,
          "height": 150,
          "url": "https://scontent.cdninstagram.com/vp/09520b3ccb800efdbed7cfd93ba20a2e/5CC23267/t51.2885-15/e35/c0.0.667.667/s150x150/47581636_238411563722121_8157556752697732901_n.jpg?_nc_ht=scontent.cdninstagram.com"
        },
        "low_resolution": {
          "width": 320,
          "height": 319,
          "url": "https://scontent.cdninstagram.com/vp/1a135a617a84784e6f2fb3f293e0307f/5CFC38DC/t51.2885-15/e35/s320x320/47581636_238411563722121_8157556752697732901_n.jpg?_nc_ht=scontent.cdninstagram.com"
        },
        "standard_resolution": {
          "width": 640,
          "height": 639,
          "url": "https://scontent.cdninstagram.com/vp/a25d6808b25a7f54d999656c30feac02/5CD0778B/t51.2885-15/sh0.08/e35/s640x640/47581636_238411563722121_8157556752697732901_n.jpg?_nc_ht=scontent.cdninstagram.com"
        }
      },
      "created_time": "1546297383",
      "caption": {
        "id": "17917876783264023",
        "text": "#BonAny2019",
        "created_time": "1546297383",
        "from": {
          "id": "31044967",
          "full_name": "Ramon",
          "profile_picture": "https://scontent.cdninstagram.com/vp/67c443456e0b9a1e8c4e86177a82ee67/5CDE2DBC/t51.2885-19/s150x150/25038116_1902832036711656_8761951227660468224_n.jpg?_nc_ht=scontent.cdninstagram.com",
          "username": "freecates"
        }
      },
      "user_has_liked": true,
      "likes": {
        "count": 33
      },
      "tags": ["bonany2019"],
      "filter": "Clarendon",
      "comments": {
        "count": 9
      },
      "type": "image",
      "link": "https://www.instagram.com/p/BsEccHFFU0D/",
      "location": {
        "latitude": 41.4099,
        "longitude": 2.1907,
        "name": "El Clot, Cataluna, Spain",
        "id": 253258441
      },
      "attribution": null,
      "users_in_photo": []
    },
    {
      "id": "1944185532440874603_31044967",
      "user": {
        "id": "31044967",
        "full_name": "Ramon",
        "profile_picture": "https://scontent.cdninstagram.com/vp/67c443456e0b9a1e8c4e86177a82ee67/5CDE2DBC/t51.2885-19/s150x150/25038116_1902832036711656_8761951227660468224_n.jpg?_nc_ht=scontent.cdninstagram.com",
        "username": "freecates"
      },
      "images": {
        "thumbnail": {
          "width": 150,
          "height": 150,
          "url": "https://scontent.cdninstagram.com/vp/47de67e969ea54cbf48b49423169690c/5CDCFEE0/t51.2885-15/e35/s150x150/47690575_161215221518606_1529771363593511767_n.jpg?_nc_ht=scontent.cdninstagram.com"
        },
        "low_resolution": {
          "width": 320,
          "height": 320,
          "url": "https://scontent.cdninstagram.com/vp/f010ca1cd996613a98d43b19630c1653/5CC4B010/t51.2885-15/e35/s320x320/47690575_161215221518606_1529771363593511767_n.jpg?_nc_ht=scontent.cdninstagram.com"
        },
        "standard_resolution": {
          "width": 640,
          "height": 640,
          "url": "https://scontent.cdninstagram.com/vp/23abc8e56e177df2a6e65fbaffc8058c/5CC4AF47/t51.2885-15/sh0.08/e35/s640x640/47690575_161215221518606_1529771363593511767_n.jpg?_nc_ht=scontent.cdninstagram.com"
        }
      },
      "created_time": "1545984997",
      "caption": {
        "id": "18016144114053213",
        "text": "Feels like 3!",
        "created_time": "1545984997",
        "from": {
          "id": "31044967",
          "full_name": "Ramon",
          "profile_picture": "https://scontent.cdninstagram.com/vp/67c443456e0b9a1e8c4e86177a82ee67/5CDE2DBC/t51.2885-19/s150x150/25038116_1902832036711656_8761951227660468224_n.jpg?_nc_ht=scontent.cdninstagram.com",
          "username": "freecates"
        }
      },
      "user_has_liked": true,
      "likes": {
        "count": 12
      },
      "tags": [],
      "filter": "Gingham",
      "comments": {
        "count": 3
      },
      "type": "image",
      "link": "https://www.instagram.com/p/Br7InDml45r/",
      "location": {
        "latitude": 41.548333333333,
        "longitude": 2.1075,
        "name": "Sabadell",
        "id": 541096
      },
      "attribution": null,
      "users_in_photo": []
    },
    {
      "id": "1942140277797827315_31044967",
      "user": {
        "id": "31044967",
        "full_name": "Ramon",
        "profile_picture": "https://scontent.cdninstagram.com/vp/67c443456e0b9a1e8c4e86177a82ee67/5CDE2DBC/t51.2885-19/s150x150/25038116_1902832036711656_8761951227660468224_n.jpg?_nc_ht=scontent.cdninstagram.com",
        "username": "freecates"
      },
      "images": {
        "thumbnail": {
          "width": 150,
          "height": 150,
          "url": "https://scontent.cdninstagram.com/vp/84d68dacd10401fb2ff0810b63828a3b/5CCA2EDA/t51.2885-15/e35/s150x150/47583712_615303178928002_1837966829488571206_n.jpg?_nc_ht=scontent.cdninstagram.com"
        },
        "low_resolution": {
          "width": 320,
          "height": 320,
          "url": "https://scontent.cdninstagram.com/vp/6043c062b98e339d498b3ef903ba427a/5CDEEF2A/t51.2885-15/e35/s320x320/47583712_615303178928002_1837966829488571206_n.jpg?_nc_ht=scontent.cdninstagram.com"
        },
        "standard_resolution": {
          "width": 640,
          "height": 640,
          "url": "https://scontent.cdninstagram.com/vp/fa632c77ae6f7fd574562d57c8f9f126/5CDEAE7D/t51.2885-15/sh0.08/e35/s640x640/47583712_615303178928002_1837966829488571206_n.jpg?_nc_ht=scontent.cdninstagram.com"
        }
      },
      "created_time": "1545741184",
      "caption": {
        "id": "17924881684247655",
        "text": "Bon i 🌟 Nadal a tothom!",
        "created_time": "1545741184",
        "from": {
          "id": "31044967",
          "full_name": "Ramon",
          "profile_picture": "https://scontent.cdninstagram.com/vp/67c443456e0b9a1e8c4e86177a82ee67/5CDE2DBC/t51.2885-19/s150x150/25038116_1902832036711656_8761951227660468224_n.jpg?_nc_ht=scontent.cdninstagram.com",
          "username": "freecates"
        }
      },
      "user_has_liked": true,
      "likes": {
        "count": 22
      },
      "tags": [],
      "filter": "Clarendon",
      "comments": {
        "count": 2
      },
      "type": "image",
      "link": "https://www.instagram.com/p/Brz3kryHjLz/",
      "location": {
        "latitude": 42.536222182378,
        "longitude": 1.4912378022486,
        "name": "Andorra, Vall Nord",
        "id": 713587193
      },
      "attribution": null,
      "users_in_photo": []
    },
    {
      "id": "1941708104263317726_31044967",
      "user": {
        "id": "31044967",
        "full_name": "Ramon",
        "profile_picture": "https://scontent.cdninstagram.com/vp/67c443456e0b9a1e8c4e86177a82ee67/5CDE2DBC/t51.2885-19/s150x150/25038116_1902832036711656_8761951227660468224_n.jpg?_nc_ht=scontent.cdninstagram.com",
        "username": "freecates"
      },
      "images": {
        "thumbnail": {
          "width": 150,
          "height": 150,
          "url": "https://scontent.cdninstagram.com/vp/1d63257cb48c5b66331bfff46fbc5792/5CCDE24B/t51.2885-15/e35/s150x150/46962005_1945157828930939_8905601693581743473_n.jpg?_nc_ht=scontent.cdninstagram.com"
        },
        "low_resolution": {
          "width": 320,
          "height": 320,
          "url": "https://scontent.cdninstagram.com/vp/3fb40d323cb5e4133a40fbfe53d7ef2b/5CBB2D33/t51.2885-15/e35/s320x320/46962005_1945157828930939_8905601693581743473_n.jpg?_nc_ht=scontent.cdninstagram.com"
        },
        "standard_resolution": {
          "width": 640,
          "height": 640,
          "url": "https://scontent.cdninstagram.com/vp/42b416b6706c4c8419b88b44a54bc4de/5CFF29CE/t51.2885-15/sh0.08/e35/s640x640/46962005_1945157828930939_8905601693581743473_n.jpg?_nc_ht=scontent.cdninstagram.com"
        }
      },
      "created_time": "1545689665",
      "caption": {
        "id": "17859237148307546",
        "text": "L'elf Nicky",
        "created_time": "1545689665",
        "from": {
          "id": "31044967",
          "full_name": "Ramon",
          "profile_picture": "https://scontent.cdninstagram.com/vp/67c443456e0b9a1e8c4e86177a82ee67/5CDE2DBC/t51.2885-19/s150x150/25038116_1902832036711656_8761951227660468224_n.jpg?_nc_ht=scontent.cdninstagram.com",
          "username": "freecates"
        }
      },
      "user_has_liked": true,
      "likes": {
        "count": 17
      },
      "tags": [],
      "filter": "Normal",
      "comments": {
        "count": 1
      },
      "type": "image",
      "link": "https://www.instagram.com/p/BryVTu0HLje/",
      "location": {
        "latitude": 42.544166666667,
        "longitude": 1.5163888888889,
        "name": "La Massana",
        "id": 511852
      },
      "attribution": null,
      "users_in_photo": []
    },
    {
      "id": "1941677079449778890_31044967",
      "user": {
        "id": "31044967",
        "full_name": "Ramon",
        "profile_picture": "https://scontent.cdninstagram.com/vp/67c443456e0b9a1e8c4e86177a82ee67/5CDE2DBC/t51.2885-19/s150x150/25038116_1902832036711656_8761951227660468224_n.jpg?_nc_ht=scontent.cdninstagram.com",
        "username": "freecates"
      },
      "images": {
        "thumbnail": {
          "width": 150,
          "height": 150,
          "url": "https://scontent.cdninstagram.com/vp/790d166f21197467e21b106abe2734a6/5CD38981/t51.2885-15/e35/c0.0.974.974/s150x150/47191943_159837808312930_3223622646239262702_n.jpg?_nc_ht=scontent.cdninstagram.com"
        },
        "low_resolution": {
          "width": 320,
          "height": 320,
          "url": "https://scontent.cdninstagram.com/vp/404d6aa069622a058a52132f44b33704/5CCA1D56/t51.2885-15/e35/p320x320/47191943_159837808312930_3223622646239262702_n.jpg?_nc_ht=scontent.cdninstagram.com"
        },
        "standard_resolution": {
          "width": 640,
          "height": 640,
          "url": "https://scontent.cdninstagram.com/vp/91d36bf2bd08e9de2d6e0670f029e224/5CB95801/t51.2885-15/sh0.08/e35/p640x640/47191943_159837808312930_3223622646239262702_n.jpg?_nc_ht=scontent.cdninstagram.com"
        }
      },
      "created_time": "1545685966",
      "caption": {
        "id": "18006491545079857",
        "text": "Bon Nadal!",
        "created_time": "1545685966",
        "from": {
          "id": "31044967",
          "full_name": "Ramon",
          "profile_picture": "https://scontent.cdninstagram.com/vp/67c443456e0b9a1e8c4e86177a82ee67/5CDE2DBC/t51.2885-19/s150x150/25038116_1902832036711656_8761951227660468224_n.jpg?_nc_ht=scontent.cdninstagram.com",
          "username": "freecates"
        }
      },
      "user_has_liked": true,
      "likes": {
        "count": 23
      },
      "tags": [],
      "filter": "Clarendon",
      "comments": {
        "count": 2
      },
      "type": "image",
      "link": "https://www.instagram.com/p/BryOQQtHzrK/",
      "location": {
        "latitude": 42.544166666667,
        "longitude": 1.5163888888889,
        "name": "La Massana",
        "id": 511852
      },
      "attribution": null,
      "users_in_photo": []
    },
    {
      "id": "1940687707812339037_31044967",
      "user": {
        "id": "31044967",
        "full_name": "Ramon",
        "profile_picture": "https://scontent.cdninstagram.com/vp/67c443456e0b9a1e8c4e86177a82ee67/5CDE2DBC/t51.2885-19/s150x150/25038116_1902832036711656_8761951227660468224_n.jpg?_nc_ht=scontent.cdninstagram.com",
        "username": "freecates"
      },
      "images": {
        "thumbnail": {
          "width": 150,
          "height": 150,
          "url": "https://scontent.cdninstagram.com/vp/6cba05ebb481b4570b1145888ea7949b/5CCE8789/t51.2885-15/e35/c32.0.1015.1015/s150x150/47135868_1164376247060565_9008515038656320047_n.jpg?_nc_ht=scontent.cdninstagram.com"
        },
        "low_resolution": {
          "width": 320,
          "height": 300,
          "url": "https://scontent.cdninstagram.com/vp/234dce9f78c83bbf09b9dfe53deb75cd/5CC66D92/t51.2885-15/e35/s320x320/47135868_1164376247060565_9008515038656320047_n.jpg?_nc_ht=scontent.cdninstagram.com"
        },
        "standard_resolution": {
          "width": 640,
          "height": 601,
          "url": "https://scontent.cdninstagram.com/vp/8e0a365cc32c03ad7644d5b8845ff071/5CD2866F/t51.2885-15/sh0.08/e35/s640x640/47135868_1164376247060565_9008515038656320047_n.jpg?_nc_ht=scontent.cdninstagram.com"
        }
      },
      "created_time": "1545568024",
      "caption": {
        "id": "17984243362144521",
        "text": "Relaxing 🍺.",
        "created_time": "1545568024",
        "from": {
          "id": "31044967",
          "full_name": "Ramon",
          "profile_picture": "https://scontent.cdninstagram.com/vp/67c443456e0b9a1e8c4e86177a82ee67/5CDE2DBC/t51.2885-19/s150x150/25038116_1902832036711656_8761951227660468224_n.jpg?_nc_ht=scontent.cdninstagram.com",
          "username": "freecates"
        }
      },
      "user_has_liked": true,
      "likes": {
        "count": 26
      },
      "tags": [],
      "filter": "Clarendon",
      "comments": {
        "count": 0
      },
      "type": "image",
      "link": "https://www.instagram.com/p/BrutTAkHx1d/",
      "location": {
        "latitude": 42.536222182378,
        "longitude": 1.4912378022486,
        "name": "Andorra, Vall Nord",
        "id": 713587193
      },
      "attribution": null,
      "users_in_photo": []
    },
    {
      "id": "1935490307631352385_31044967",
      "user": {
        "id": "31044967",
        "full_name": "Ramon",
        "profile_picture": "https://scontent.cdninstagram.com/vp/67c443456e0b9a1e8c4e86177a82ee67/5CDE2DBC/t51.2885-19/s150x150/25038116_1902832036711656_8761951227660468224_n.jpg?_nc_ht=scontent.cdninstagram.com",
        "username": "freecates"
      },
      "images": {
        "thumbnail": {
          "width": 150,
          "height": 150,
          "url": "https://scontent.cdninstagram.com/vp/85e39db3f9edbaf97d5b711e67a6c5bb/5CFE258B/t51.2885-15/e35/s150x150/45329236_792023694476291_5107688363723448588_n.jpg?_nc_ht=scontent.cdninstagram.com"
        },
        "low_resolution": {
          "width": 320,
          "height": 320,
          "url": "https://scontent.cdninstagram.com/vp/1e2fceb639e701972b470f36c6b61833/5CCB997B/t51.2885-15/e35/s320x320/45329236_792023694476291_5107688363723448588_n.jpg?_nc_ht=scontent.cdninstagram.com"
        },
        "standard_resolution": {
          "width": 640,
          "height": 640,
          "url": "https://scontent.cdninstagram.com/vp/2bb2a6b21e74c90c51c85b8d7c4c9030/5CDA5E2C/t51.2885-15/sh0.08/e35/s640x640/45329236_792023694476291_5107688363723448588_n.jpg?_nc_ht=scontent.cdninstagram.com"
        }
      },
      "created_time": "1544948446",
      "caption": {
        "id": "17974011637168705",
        "text": "@lanauva_sbd vista frontal.",
        "created_time": "1544948446",
        "from": {
          "id": "31044967",
          "full_name": "Ramon",
          "profile_picture": "https://scontent.cdninstagram.com/vp/67c443456e0b9a1e8c4e86177a82ee67/5CDE2DBC/t51.2885-19/s150x150/25038116_1902832036711656_8761951227660468224_n.jpg?_nc_ht=scontent.cdninstagram.com",
          "username": "freecates"
        }
      },
      "user_has_liked": true,
      "likes": {
        "count": 10
      },
      "tags": [],
      "filter": "Normal",
      "comments": {
        "count": 0
      },
      "type": "image",
      "link": "https://www.instagram.com/p/BrcPi4clApB/",
      "location": null,
      "attribution": null,
      "users_in_photo": []
    },
    {
      "id": "1930059078182587867_31044967",
      "user": {
        "id": "31044967",
        "full_name": "Ramon",
        "profile_picture": "https://scontent.cdninstagram.com/vp/67c443456e0b9a1e8c4e86177a82ee67/5CDE2DBC/t51.2885-19/s150x150/25038116_1902832036711656_8761951227660468224_n.jpg?_nc_ht=scontent.cdninstagram.com",
        "username": "freecates"
      },
      "images": {
        "thumbnail": {
          "width": 150,
          "height": 150,
          "url": "https://scontent.cdninstagram.com/vp/8acaf8f2fcf7efd3ee0ed7506baf69c7/5CC54BBC/t51.2885-15/e35/s150x150/45733529_1939255572858625_2862295298317548437_n.jpg?_nc_ht=scontent.cdninstagram.com"
        },
        "low_resolution": {
          "width": 320,
          "height": 320,
          "url": "https://scontent.cdninstagram.com/vp/c29aeb837ddb2fac4951d7fc1e21bf28/5CFE27C4/t51.2885-15/e35/s320x320/45733529_1939255572858625_2862295298317548437_n.jpg?_nc_ht=scontent.cdninstagram.com"
        },
        "standard_resolution": {
          "width": 640,
          "height": 640,
          "url": "https://scontent.cdninstagram.com/vp/97de6b34580b416003519a25f3dd11fa/5CBF5939/t51.2885-15/sh0.08/e35/s640x640/45733529_1939255572858625_2862295298317548437_n.jpg?_nc_ht=scontent.cdninstagram.com"
        }
      },
      "created_time": "1544300993",
      "caption": {
        "id": "17945363350210952",
        "text": "Descans | #drmartens1461",
        "created_time": "1544300993",
        "from": {
          "id": "31044967",
          "full_name": "Ramon",
          "profile_picture": "https://scontent.cdninstagram.com/vp/67c443456e0b9a1e8c4e86177a82ee67/5CDE2DBC/t51.2885-19/s150x150/25038116_1902832036711656_8761951227660468224_n.jpg?_nc_ht=scontent.cdninstagram.com",
          "username": "freecates"
        }
      },
      "user_has_liked": true,
      "likes": {
        "count": 24
      },
      "tags": ["drmartens1461"],
      "filter": "Clarendon",
      "comments": {
        "count": 0
      },
      "type": "image",
      "link": "https://www.instagram.com/p/BrI8oF2l03b/",
      "location": null,
      "attribution": null,
      "users_in_photo": []
    },
    {
      "id": "1921700761387289624_31044967",
      "user": {
        "id": "31044967",
        "full_name": "Ramon",
        "profile_picture": "https://scontent.cdninstagram.com/vp/67c443456e0b9a1e8c4e86177a82ee67/5CDE2DBC/t51.2885-19/s150x150/25038116_1902832036711656_8761951227660468224_n.jpg?_nc_ht=scontent.cdninstagram.com",
        "username": "freecates"
      },
      "images": {
        "thumbnail": {
          "width": 150,
          "height": 150,
          "url": "https://scontent.cdninstagram.com/vp/f6fa3bd69036b1877ad5a55ec88699a8/5CDA1838/t51.2885-15/e35/s150x150/45275605_259597258053887_2889181536779514212_n.jpg?_nc_ht=scontent.cdninstagram.com"
        },
        "low_resolution": {
          "width": 320,
          "height": 320,
          "url": "https://scontent.cdninstagram.com/vp/50eb899d9b446fc3aaac69ff5de53f42/5CC7F7C8/t51.2885-15/e35/s320x320/45275605_259597258053887_2889181536779514212_n.jpg?_nc_ht=scontent.cdninstagram.com"
        },
        "standard_resolution": {
          "width": 640,
          "height": 640,
          "url": "https://scontent.cdninstagram.com/vp/06cb5cea1a951554bfbdd00b1496a894/5CCEC29F/t51.2885-15/sh0.08/e35/s640x640/45275605_259597258053887_2889181536779514212_n.jpg?_nc_ht=scontent.cdninstagram.com"
        }
      },
      "created_time": "1543304604",
      "caption": {
        "id": "18006529558013400",
        "text": "#Frescota",
        "created_time": "1543304604",
        "from": {
          "id": "31044967",
          "full_name": "Ramon",
          "profile_picture": "https://scontent.cdninstagram.com/vp/67c443456e0b9a1e8c4e86177a82ee67/5CDE2DBC/t51.2885-19/s150x150/25038116_1902832036711656_8761951227660468224_n.jpg?_nc_ht=scontent.cdninstagram.com",
          "username": "freecates"
        }
      },
      "user_has_liked": true,
      "likes": {
        "count": 7
      },
      "tags": ["frescota"],
      "filter": "Normal",
      "comments": {
        "count": 0
      },
      "type": "image",
      "link": "https://www.instagram.com/p/BqrQKkvFkwY/",
      "location": {
        "latitude": 41.548333333333,
        "longitude": 2.1075,
        "name": "Sabadell",
        "id": 541096
      },
      "attribution": null,
      "users_in_photo": []
    },
    {
      "id": "1919578174330907233_31044967",
      "user": {
        "id": "31044967",
        "full_name": "Ramon",
        "profile_picture": "https://scontent.cdninstagram.com/vp/67c443456e0b9a1e8c4e86177a82ee67/5CDE2DBC/t51.2885-19/s150x150/25038116_1902832036711656_8761951227660468224_n.jpg?_nc_ht=scontent.cdninstagram.com",
        "username": "freecates"
      },
      "images": {
        "thumbnail": {
          "width": 150,
          "height": 150,
          "url": "https://scontent.cdninstagram.com/vp/ea334a88cb7d3a2964a65c5f3fe7cb33/5CD2E9E9/t51.2885-15/e35/s150x150/44707923_2328362940539113_2115488906823415481_n.jpg?_nc_ht=scontent.cdninstagram.com"
        },
        "low_resolution": {
          "width": 320,
          "height": 320,
          "url": "https://scontent.cdninstagram.com/vp/7f611a404e5787cc010f551fdf4abe1a/5CFC0491/t51.2885-15/e35/s320x320/44707923_2328362940539113_2115488906823415481_n.jpg?_nc_ht=scontent.cdninstagram.com"
        },
        "standard_resolution": {
          "width": 640,
          "height": 640,
          "url": "https://scontent.cdninstagram.com/vp/a2050a0a10952748ee6bc66c354393d9/5CFDE46C/t51.2885-15/sh0.08/e35/s640x640/44707923_2328362940539113_2115488906823415481_n.jpg?_nc_ht=scontent.cdninstagram.com"
        }
      },
      "created_time": "1543051572",
      "caption": {
        "id": "17973638203181093",
        "text": "Llacet mexicà . Un regal de l' @elivazquezabarca amb molt d'amor| #muestrademodamexicana  by @pajaritas.mx",
        "created_time": "1543051572",
        "from": {
          "id": "31044967",
          "full_name": "Ramon",
          "profile_picture": "https://scontent.cdninstagram.com/vp/67c443456e0b9a1e8c4e86177a82ee67/5CDE2DBC/t51.2885-19/s150x150/25038116_1902832036711656_8761951227660468224_n.jpg?_nc_ht=scontent.cdninstagram.com",
          "username": "freecates"
        }
      },
      "user_has_liked": true,
      "likes": {
        "count": 12
      },
      "tags": ["muestrademodamexicana"],
      "filter": "Normal",
      "comments": {
        "count": 3
      },
      "type": "carousel",
      "link": "https://www.instagram.com/p/Bqjti3fliph/",
      "location": {
        "latitude": 41.412126228,
        "longitude": 2.182958545,
        "name": "Barcelona Ciutat",
        "id": 235051503
      },
      "attribution": null,
      "users_in_photo": [],
      "carousel_media": [
        {
          "images": {
            "thumbnail": {
              "width": 150,
              "height": 150,
              "url": "https://scontent.cdninstagram.com/vp/ea334a88cb7d3a2964a65c5f3fe7cb33/5CD2E9E9/t51.2885-15/e35/s150x150/44707923_2328362940539113_2115488906823415481_n.jpg?_nc_ht=scontent.cdninstagram.com"
            },
            "low_resolution": {
              "width": 320,
              "height": 320,
              "url": "https://scontent.cdninstagram.com/vp/7f611a404e5787cc010f551fdf4abe1a/5CFC0491/t51.2885-15/e35/s320x320/44707923_2328362940539113_2115488906823415481_n.jpg?_nc_ht=scontent.cdninstagram.com"
            },
            "standard_resolution": {
              "width": 640,
              "height": 640,
              "url": "https://scontent.cdninstagram.com/vp/a2050a0a10952748ee6bc66c354393d9/5CFDE46C/t51.2885-15/sh0.08/e35/s640x640/44707923_2328362940539113_2115488906823415481_n.jpg?_nc_ht=scontent.cdninstagram.com"
            }
          },
          "users_in_photo": [],
          "type": "image"
        },
        {
          "images": {
            "thumbnail": {
              "width": 150,
              "height": 150,
              "url": "https://scontent.cdninstagram.com/vp/697b39b20bf2b74f54db17fbed578be4/5CFE8EBA/t51.2885-15/e35/s150x150/45640708_2739723112975728_1885103413628916619_n.jpg?_nc_ht=scontent.cdninstagram.com"
            },
            "low_resolution": {
              "width": 320,
              "height": 320,
              "url": "https://scontent.cdninstagram.com/vp/bee6d9e409954dca107595c14d6c3df7/5CCE92C2/t51.2885-15/e35/s320x320/45640708_2739723112975728_1885103413628916619_n.jpg?_nc_ht=scontent.cdninstagram.com"
            },
            "standard_resolution": {
              "width": 640,
              "height": 640,
              "url": "https://scontent.cdninstagram.com/vp/de6c377f92458a3688361c344e295f0b/5CDDE03F/t51.2885-15/sh0.08/e35/s640x640/45640708_2739723112975728_1885103413628916619_n.jpg?_nc_ht=scontent.cdninstagram.com"
            }
          },
          "users_in_photo": [],
          "type": "image"
        },
        {
          "images": {
            "thumbnail": {
              "width": 150,
              "height": 150,
              "url": "https://scontent.cdninstagram.com/vp/3251a33d2e03b47b3d65076f8497e851/5CBFEEA6/t51.2885-15/e35/s150x150/44736182_2178925289061935_4347331977650783500_n.jpg?_nc_ht=scontent.cdninstagram.com"
            },
            "low_resolution": {
              "width": 320,
              "height": 320,
              "url": "https://scontent.cdninstagram.com/vp/643c424de0d671efde1c69bb88bab0d7/5CFBBEDE/t51.2885-15/e35/s320x320/44736182_2178925289061935_4347331977650783500_n.jpg?_nc_ht=scontent.cdninstagram.com"
            },
            "standard_resolution": {
              "width": 640,
              "height": 640,
              "url": "https://scontent.cdninstagram.com/vp/a3c7ca0347c04a45876b1b8d52c51c72/5CFCEC23/t51.2885-15/sh0.08/e35/s640x640/44736182_2178925289061935_4347331977650783500_n.jpg?_nc_ht=scontent.cdninstagram.com"
            }
          },
          "users_in_photo": [],
          "type": "image"
        },
        {
          "images": {
            "thumbnail": {
              "width": 150,
              "height": 150,
              "url": "https://scontent.cdninstagram.com/vp/050e29f3946c876c2dbdfa8d1d5a5117/5CCCC88C/t51.2885-15/e35/s150x150/43331077_1146094988876989_5690165315125854790_n.jpg?_nc_ht=scontent.cdninstagram.com"
            },
            "low_resolution": {
              "width": 320,
              "height": 320,
              "url": "https://scontent.cdninstagram.com/vp/4fc091724217ac59445dd10ed0c80f47/5CDC35F4/t51.2885-15/e35/s320x320/43331077_1146094988876989_5690165315125854790_n.jpg?_nc_ht=scontent.cdninstagram.com"
            },
            "standard_resolution": {
              "width": 640,
              "height": 640,
              "url": "https://scontent.cdninstagram.com/vp/8cb5af3dfc778503558380f0f41ac168/5CDF6309/t51.2885-15/sh0.08/e35/s640x640/43331077_1146094988876989_5690165315125854790_n.jpg?_nc_ht=scontent.cdninstagram.com"
            }
          },
          "users_in_photo": [],
          "type": "image"
        }
      ]
    },
    {
      "id": "1917700031630293682_31044967",
      "user": {
        "id": "31044967",
        "full_name": "Ramon",
        "profile_picture": "https://scontent.cdninstagram.com/vp/67c443456e0b9a1e8c4e86177a82ee67/5CDE2DBC/t51.2885-19/s150x150/25038116_1902832036711656_8761951227660468224_n.jpg?_nc_ht=scontent.cdninstagram.com",
        "username": "freecates"
      },
      "images": {
        "thumbnail": {
          "width": 150,
          "height": 150,
          "url": "https://scontent.cdninstagram.com/vp/4051a2884cbc19c3b9411028b08bafb3/5CBE2FB7/t51.2885-15/e35/s150x150/45361221_2207104432655438_1867573435175105774_n.jpg?_nc_ht=scontent.cdninstagram.com"
        },
        "low_resolution": {
          "width": 320,
          "height": 320,
          "url": "https://scontent.cdninstagram.com/vp/63faccc0009e0313d484d9000f20a1ac/5CBF69CF/t51.2885-15/e35/s320x320/45361221_2207104432655438_1867573435175105774_n.jpg?_nc_ht=scontent.cdninstagram.com"
        },
        "standard_resolution": {
          "width": 640,
          "height": 640,
          "url": "https://scontent.cdninstagram.com/vp/9698069f32d3c964951a033e64748d81/5CC69C32/t51.2885-15/sh0.08/e35/s640x640/45361221_2207104432655438_1867573435175105774_n.jpg?_nc_ht=scontent.cdninstagram.com"
        }
      },
      "created_time": "1542827680",
      "caption": {
        "id": "17973187915192704",
        "text": "#muestrademodamexicana",
        "created_time": "1542827680",
        "from": {
          "id": "31044967",
          "full_name": "Ramon",
          "profile_picture": "https://scontent.cdninstagram.com/vp/67c443456e0b9a1e8c4e86177a82ee67/5CDE2DBC/t51.2885-19/s150x150/25038116_1902832036711656_8761951227660468224_n.jpg?_nc_ht=scontent.cdninstagram.com",
          "username": "freecates"
        }
      },
      "user_has_liked": true,
      "likes": {
        "count": 10
      },
      "tags": ["muestrademodamexicana"],
      "filter": "Clarendon",
      "comments": {
        "count": 0
      },
      "type": "image",
      "link": "https://www.instagram.com/p/BqdCgSzFDqy/",
      "location": {
        "latitude": 41.38591,
        "longitude": 2.171409,
        "name": "Church of Santa Anna",
        "id": 293760374
      },
      "attribution": null,
      "users_in_photo": []
    },
    {
      "id": "1917693721056646935_31044967",
      "user": {
        "id": "31044967",
        "full_name": "Ramon",
        "profile_picture": "https://scontent.cdninstagram.com/vp/67c443456e0b9a1e8c4e86177a82ee67/5CDE2DBC/t51.2885-19/s150x150/25038116_1902832036711656_8761951227660468224_n.jpg?_nc_ht=scontent.cdninstagram.com",
        "username": "freecates"
      },
      "images": {
        "thumbnail": {
          "width": 150,
          "height": 150,
          "url": "https://scontent.cdninstagram.com/vp/53546877307e677aea647fcf27b4bd08/5CDF5DB4/t51.2885-15/e35/s150x150/44785402_1715142798595439_8238271224126837953_n.jpg?_nc_ht=scontent.cdninstagram.com"
        },
        "low_resolution": {
          "width": 320,
          "height": 320,
          "url": "https://scontent.cdninstagram.com/vp/ee4e45b7d686231ceece1686fa8a6973/5CFCD5CC/t51.2885-15/e35/s320x320/44785402_1715142798595439_8238271224126837953_n.jpg?_nc_ht=scontent.cdninstagram.com"
        },
        "standard_resolution": {
          "width": 640,
          "height": 640,
          "url": "https://scontent.cdninstagram.com/vp/39e95d158ca563814055b753f4b4b994/5CCC3631/t51.2885-15/sh0.08/e35/s640x640/44785402_1715142798595439_8238271224126837953_n.jpg?_nc_ht=scontent.cdninstagram.com"
        }
      },
      "created_time": "1542826927",
      "caption": {
        "id": "17987953381099554",
        "text": "#muestrademodamexicana",
        "created_time": "1542826927",
        "from": {
          "id": "31044967",
          "full_name": "Ramon",
          "profile_picture": "https://scontent.cdninstagram.com/vp/67c443456e0b9a1e8c4e86177a82ee67/5CDE2DBC/t51.2885-19/s150x150/25038116_1902832036711656_8761951227660468224_n.jpg?_nc_ht=scontent.cdninstagram.com",
          "username": "freecates"
        }
      },
      "user_has_liked": true,
      "likes": {
        "count": 14
      },
      "tags": ["muestrademodamexicana"],
      "filter": "Clarendon",
      "comments": {
        "count": 0
      },
      "type": "image",
      "link": "https://www.instagram.com/p/BqdBEdnlBcX/",
      "location": {
        "latitude": 41.38591,
        "longitude": 2.171409,
        "name": "Church of Santa Anna",
        "id": 293760374
      },
      "attribution": null,
      "users_in_photo": []
    },
    {
      "id": "1917689519244869213_31044967",
      "user": {
        "id": "31044967",
        "full_name": "Ramon",
        "profile_picture": "https://scontent.cdninstagram.com/vp/67c443456e0b9a1e8c4e86177a82ee67/5CDE2DBC/t51.2885-19/s150x150/25038116_1902832036711656_8761951227660468224_n.jpg?_nc_ht=scontent.cdninstagram.com",
        "username": "freecates"
      },
      "images": {
        "thumbnail": {
          "width": 150,
          "height": 150,
          "url": "https://scontent.cdninstagram.com/vp/fe0e8ea14a4fc37b68f1609c5e501d29/5CCC17DB/t51.2885-15/e35/s150x150/44917777_298391794112871_2924768164221696987_n.jpg?_nc_ht=scontent.cdninstagram.com"
        },
        "low_resolution": {
          "width": 320,
          "height": 320,
          "url": "https://scontent.cdninstagram.com/vp/a455e116455212f7f400e0ff8b53d411/5CD3502B/t51.2885-15/e35/s320x320/44917777_298391794112871_2924768164221696987_n.jpg?_nc_ht=scontent.cdninstagram.com"
        },
        "standard_resolution": {
          "width": 640,
          "height": 640,
          "url": "https://scontent.cdninstagram.com/vp/58c8ebcecce7c2fa1c4f3fb8c4aafa2c/5CFCC57C/t51.2885-15/sh0.08/e35/s640x640/44917777_298391794112871_2924768164221696987_n.jpg?_nc_ht=scontent.cdninstagram.com"
        }
      },
      "created_time": "1542826426",
      "caption": {
        "id": "17938494691219329",
        "text": "#muestrademodamexicana",
        "created_time": "1542826426",
        "from": {
          "id": "31044967",
          "full_name": "Ramon",
          "profile_picture": "https://scontent.cdninstagram.com/vp/67c443456e0b9a1e8c4e86177a82ee67/5CDE2DBC/t51.2885-19/s150x150/25038116_1902832036711656_8761951227660468224_n.jpg?_nc_ht=scontent.cdninstagram.com",
          "username": "freecates"
        }
      },
      "user_has_liked": true,
      "likes": {
        "count": 8
      },
      "tags": ["muestrademodamexicana"],
      "filter": "Clarendon",
      "comments": {
        "count": 0
      },
      "type": "image",
      "link": "https://www.instagram.com/p/BqdAHUYFH5d/",
      "location": {
        "latitude": 41.38591,
        "longitude": 2.171409,
        "name": "Church of Santa Anna",
        "id": 293760374
      },
      "attribution": null,
      "users_in_photo": []
    },
    {
      "id": "1917687362743622067_31044967",
      "user": {
        "id": "31044967",
        "full_name": "Ramon",
        "profile_picture": "https://scontent.cdninstagram.com/vp/67c443456e0b9a1e8c4e86177a82ee67/5CDE2DBC/t51.2885-19/s150x150/25038116_1902832036711656_8761951227660468224_n.jpg?_nc_ht=scontent.cdninstagram.com",
        "username": "freecates"
      },
      "images": {
        "thumbnail": {
          "width": 150,
          "height": 150,
          "url": "https://scontent.cdninstagram.com/vp/71393a63bbc4b3dc5506ac8e50d687b1/5CCD22A0/t51.2885-15/e35/s150x150/44448163_291957704762911_6557849176947650393_n.jpg?_nc_ht=scontent.cdninstagram.com"
        },
        "low_resolution": {
          "width": 320,
          "height": 320,
          "url": "https://scontent.cdninstagram.com/vp/478779e9efe17224b3d99645483fbb5a/5CFCA850/t51.2885-15/e35/s320x320/44448163_291957704762911_6557849176947650393_n.jpg?_nc_ht=scontent.cdninstagram.com"
        },
        "standard_resolution": {
          "width": 640,
          "height": 640,
          "url": "https://scontent.cdninstagram.com/vp/0fd05a65388b47e513ebafa48735cc92/5CBC8707/t51.2885-15/sh0.08/e35/s640x640/44448163_291957704762911_6557849176947650393_n.jpg?_nc_ht=scontent.cdninstagram.com"
        }
      },
      "created_time": "1542826169",
      "caption": {
        "id": "17881120237285773",
        "text": "#muestrademodamexicana",
        "created_time": "1542826169",
        "from": {
          "id": "31044967",
          "full_name": "Ramon",
          "profile_picture": "https://scontent.cdninstagram.com/vp/67c443456e0b9a1e8c4e86177a82ee67/5CDE2DBC/t51.2885-19/s150x150/25038116_1902832036711656_8761951227660468224_n.jpg?_nc_ht=scontent.cdninstagram.com",
          "username": "freecates"
        }
      },
      "user_has_liked": true,
      "likes": {
        "count": 6
      },
      "tags": ["muestrademodamexicana"],
      "filter": "Clarendon",
      "comments": {
        "count": 0
      },
      "type": "image",
      "link": "https://www.instagram.com/p/Bqc_n7-ltmz/",
      "location": {
        "latitude": 41.38591,
        "longitude": 2.171409,
        "name": "Church of Santa Anna",
        "id": 293760374
      },
      "attribution": null,
      "users_in_photo": []
    },
    {
      "id": "1917679639402581405_31044967",
      "user": {
        "id": "31044967",
        "full_name": "Ramon",
        "profile_picture": "https://scontent.cdninstagram.com/vp/67c443456e0b9a1e8c4e86177a82ee67/5CDE2DBC/t51.2885-19/s150x150/25038116_1902832036711656_8761951227660468224_n.jpg?_nc_ht=scontent.cdninstagram.com",
        "username": "freecates"
      },
      "images": {
        "thumbnail": {
          "width": 150,
          "height": 150,
          "url": "https://scontent.cdninstagram.com/vp/7c7f5961ec073e843e5229dd13e9a0ca/5CFF371E/t51.2885-15/e35/s150x150/43371272_115617492784809_8941541282439640377_n.jpg?_nc_ht=scontent.cdninstagram.com"
        },
        "low_resolution": {
          "width": 320,
          "height": 320,
          "url": "https://scontent.cdninstagram.com/vp/c55c9952574cb76597d312c3000ff93d/5CCB04EE/t51.2885-15/e35/s320x320/43371272_115617492784809_8941541282439640377_n.jpg?_nc_ht=scontent.cdninstagram.com"
        },
        "standard_resolution": {
          "width": 640,
          "height": 640,
          "url": "https://scontent.cdninstagram.com/vp/3b01d176c6bfe6b50c3d57d0a81c20b5/5CD1FDB9/t51.2885-15/sh0.08/e35/s640x640/43371272_115617492784809_8941541282439640377_n.jpg?_nc_ht=scontent.cdninstagram.com"
        }
      },
      "created_time": "1542825249",
      "caption": {
        "id": "17895047842278100",
        "text": "#muestrademodamexicana",
        "created_time": "1542825249",
        "from": {
          "id": "31044967",
          "full_name": "Ramon",
          "profile_picture": "https://scontent.cdninstagram.com/vp/67c443456e0b9a1e8c4e86177a82ee67/5CDE2DBC/t51.2885-19/s150x150/25038116_1902832036711656_8761951227660468224_n.jpg?_nc_ht=scontent.cdninstagram.com",
          "username": "freecates"
        }
      },
      "user_has_liked": true,
      "likes": {
        "count": 5
      },
      "tags": ["muestrademodamexicana"],
      "filter": "Clarendon",
      "comments": {
        "count": 0
      },
      "type": "image",
      "link": "https://www.instagram.com/p/Bqc93jDlw2d/",
      "location": {
        "latitude": 41.38591,
        "longitude": 2.171409,
        "name": "Church of Santa Anna",
        "id": 293760374
      },
      "attribution": null,
      "users_in_photo": []
    },
    {
      "id": "1915223863069106837_31044967",
      "user": {
        "id": "31044967",
        "full_name": "Ramon",
        "profile_picture": "https://scontent.cdninstagram.com/vp/67c443456e0b9a1e8c4e86177a82ee67/5CDE2DBC/t51.2885-19/s150x150/25038116_1902832036711656_8761951227660468224_n.jpg?_nc_ht=scontent.cdninstagram.com",
        "username": "freecates"
      },
      "images": {
        "thumbnail": {
          "width": 150,
          "height": 150,
          "url": "https://scontent.cdninstagram.com/vp/cb703c05172622bfe8f51f523e5ad217/5CFDDE46/t51.2885-15/e35/c135.0.810.810/s150x150/44498270_709568379418862_5710482595617673083_n.jpg?_nc_ht=scontent.cdninstagram.com"
        },
        "low_resolution": {
          "width": 320,
          "height": 240,
          "url": "https://scontent.cdninstagram.com/vp/98c7e825f030a17234c880a12d2903e6/5CC4F9BB/t51.2885-15/e35/s320x320/44498270_709568379418862_5710482595617673083_n.jpg?_nc_ht=scontent.cdninstagram.com"
        },
        "standard_resolution": {
          "width": 640,
          "height": 480,
          "url": "https://scontent.cdninstagram.com/vp/9601dbecfb0678d10d2e13c7a7f40af9/5CB995EC/t51.2885-15/sh0.08/e35/s640x640/44498270_709568379418862_5710482595617673083_n.jpg?_nc_ht=scontent.cdninstagram.com"
        }
      },
      "created_time": "1542532497",
      "caption": {
        "id": "17968778425167579",
        "text": "Celebrant Santa Elizabeth I... Sant Xibeco!",
        "created_time": "1542532497",
        "from": {
          "id": "31044967",
          "full_name": "Ramon",
          "profile_picture": "https://scontent.cdninstagram.com/vp/67c443456e0b9a1e8c4e86177a82ee67/5CDE2DBC/t51.2885-19/s150x150/25038116_1902832036711656_8761951227660468224_n.jpg?_nc_ht=scontent.cdninstagram.com",
          "username": "freecates"
        }
      },
      "user_has_liked": true,
      "likes": {
        "count": 16
      },
      "tags": [],
      "filter": "Clarendon",
      "comments": {
        "count": 0
      },
      "type": "image",
      "link": "https://www.instagram.com/p/BqUPfTHleKV/",
      "location": {
        "latitude": 41.442975695484,
        "longitude": 2.1821165084839,
        "name": "El Camarote",
        "id": 1853493668025882
      },
      "attribution": null,
      "users_in_photo": [
        {
          "user": {
            "username": "elivazquezabarca"
          },
          "position": {
            "x": 0.7861111,
            "y": 0.5185185
          }
        },
        {
          "user": {
            "username": "mariagiil_"
          },
          "position": {
            "x": 0.6215278,
            "y": 0.46018519999999996
          }
        }
      ]
    },
    {
      "id": "1914610940089099903_31044967",
      "user": {
        "id": "31044967",
        "full_name": "Ramon",
        "profile_picture": "https://scontent.cdninstagram.com/vp/67c443456e0b9a1e8c4e86177a82ee67/5CDE2DBC/t51.2885-19/s150x150/25038116_1902832036711656_8761951227660468224_n.jpg?_nc_ht=scontent.cdninstagram.com",
        "username": "freecates"
      },
      "images": {
        "thumbnail": {
          "width": 150,
          "height": 150,
          "url": "https://scontent.cdninstagram.com/vp/7ed95009f40a1d592e1f7e3a78be19ee/5CC2F83C/t51.2885-15/e35/s150x150/43430650_1930898320549135_9118388765232839893_n.jpg?_nc_ht=scontent.cdninstagram.com"
        },
        "low_resolution": {
          "width": 320,
          "height": 320,
          "url": "https://scontent.cdninstagram.com/vp/0e056d97708e024b0525b05f14149ab7/5CBD9744/t51.2885-15/e35/s320x320/43430650_1930898320549135_9118388765232839893_n.jpg?_nc_ht=scontent.cdninstagram.com"
        },
        "standard_resolution": {
          "width": 640,
          "height": 640,
          "url": "https://scontent.cdninstagram.com/vp/4938b1d7b6e46e1abdb683130f36f07e/5CFCCFB9/t51.2885-15/sh0.08/e35/s640x640/43430650_1930898320549135_9118388765232839893_n.jpg?_nc_ht=scontent.cdninstagram.com"
        }
      },
      "created_time": "1542459431",
      "caption": {
        "id": "17975948323143185",
        "text": "#joyeuxanniversaire Luna!",
        "created_time": "1542459431",
        "from": {
          "id": "31044967",
          "full_name": "Ramon",
          "profile_picture": "https://scontent.cdninstagram.com/vp/67c443456e0b9a1e8c4e86177a82ee67/5CDE2DBC/t51.2885-19/s150x150/25038116_1902832036711656_8761951227660468224_n.jpg?_nc_ht=scontent.cdninstagram.com",
          "username": "freecates"
        }
      },
      "user_has_liked": true,
      "likes": {
        "count": 15
      },
      "tags": ["joyeuxanniversaire"],
      "filter": "Clarendon",
      "comments": {
        "count": 3
      },
      "type": "image",
      "link": "https://www.instagram.com/p/BqSEIGHFmZ_/",
      "location": {
        "latitude": 41.44107,
        "longitude": 2.2311899,
        "name": "LASER KING",
        "id": 1021693284
      },
      "attribution": null,
      "users_in_photo": [
        {
          "user": {
            "username": "lunigetvaz"
          },
          "position": {
            "x": 0.36805555,
            "y": 0.22083333
          }
        }
      ]
    },
    {
      "id": "1910196466359844163_31044967",
      "user": {
        "id": "31044967",
        "full_name": "Ramon",
        "profile_picture": "https://scontent.cdninstagram.com/vp/67c443456e0b9a1e8c4e86177a82ee67/5CDE2DBC/t51.2885-19/s150x150/25038116_1902832036711656_8761951227660468224_n.jpg?_nc_ht=scontent.cdninstagram.com",
        "username": "freecates"
      },
      "images": {
        "thumbnail": {
          "width": 150,
          "height": 150,
          "url": "https://scontent.cdninstagram.com/vp/a5da2d89db1fbb5d52ecdd73aa634be9/5CFFC1FC/t51.2885-15/e35/s150x150/42503779_193481661528460_4549324908585982908_n.jpg?_nc_ht=scontent.cdninstagram.com"
        },
        "low_resolution": {
          "width": 320,
          "height": 320,
          "url": "https://scontent.cdninstagram.com/vp/75141f9de61071d1dcce5164df6ef5ed/5CC9DB0C/t51.2885-15/e35/s320x320/42503779_193481661528460_4549324908585982908_n.jpg?_nc_ht=scontent.cdninstagram.com"
        },
        "standard_resolution": {
          "width": 640,
          "height": 640,
          "url": "https://scontent.cdninstagram.com/vp/686035818c1e630e3538c016045face8/5CBF9E5B/t51.2885-15/sh0.08/e35/s640x640/42503779_193481661528460_4549324908585982908_n.jpg?_nc_ht=scontent.cdninstagram.com"
        }
      },
      "created_time": "1541933185",
      "caption": {
        "id": "17990539996073619",
        "text": "Comença el Cercavila dels @castellersdebarcelona | #festamajor2018  #sombarcelona",
        "created_time": "1541933185",
        "from": {
          "id": "31044967",
          "full_name": "Ramon",
          "profile_picture": "https://scontent.cdninstagram.com/vp/67c443456e0b9a1e8c4e86177a82ee67/5CDE2DBC/t51.2885-19/s150x150/25038116_1902832036711656_8761951227660468224_n.jpg?_nc_ht=scontent.cdninstagram.com",
          "username": "freecates"
        }
      },
      "user_has_liked": true,
      "likes": {
        "count": 27
      },
      "tags": ["sombarcelona", "festamajor2018"],
      "filter": "Clarendon",
      "comments": {
        "count": 0
      },
      "type": "image",
      "link": "https://www.instagram.com/p/BqCYZDElb1D/",
      "location": {
        "latitude": 41.411401226493,
        "longitude": 2.1922445297241,
        "name": "Castellers de Barcelona",
        "id": 238252676
      },
      "attribution": null,
      "users_in_photo": []
    },
    {
      "id": "1909738965084568101_31044967",
      "user": {
        "id": "31044967",
        "full_name": "Ramon",
        "profile_picture": "https://scontent.cdninstagram.com/vp/67c443456e0b9a1e8c4e86177a82ee67/5CDE2DBC/t51.2885-19/s150x150/25038116_1902832036711656_8761951227660468224_n.jpg?_nc_ht=scontent.cdninstagram.com",
        "username": "freecates"
      },
      "images": {
        "thumbnail": {
          "width": 150,
          "height": 150,
          "url": "https://scontent.cdninstagram.com/vp/11eecbd13dde7c0da237d5dcf4132668/5CC0400A/t51.2885-15/e35/s150x150/44176984_103226977317828_3891688419778233623_n.jpg?_nc_ht=scontent.cdninstagram.com"
        },
        "low_resolution": {
          "width": 320,
          "height": 320,
          "url": "https://scontent.cdninstagram.com/vp/df2510d0b606a26e86158cf9de151bd8/5CDF45FA/t51.2885-15/e35/s320x320/44176984_103226977317828_3891688419778233623_n.jpg?_nc_ht=scontent.cdninstagram.com"
        },
        "standard_resolution": {
          "width": 640,
          "height": 640,
          "url": "https://scontent.cdninstagram.com/vp/40f345eacfbadb7e17a9e00a70b14f81/5CB9E0AD/t51.2885-15/sh0.08/e35/s640x640/44176984_103226977317828_3891688419778233623_n.jpg?_nc_ht=scontent.cdninstagram.com"
        }
      },
      "created_time": "1541878646",
      "caption": {
        "id": "17967822910155032",
        "text": "12 anys del @budhha_10__",
        "created_time": "1541878646",
        "from": {
          "id": "31044967",
          "full_name": "Ramon",
          "profile_picture": "https://scontent.cdninstagram.com/vp/67c443456e0b9a1e8c4e86177a82ee67/5CDE2DBC/t51.2885-19/s150x150/25038116_1902832036711656_8761951227660468224_n.jpg?_nc_ht=scontent.cdninstagram.com",
          "username": "freecates"
        }
      },
      "user_has_liked": true,
      "likes": {
        "count": 17
      },
      "tags": [],
      "filter": "Clarendon",
      "comments": {
        "count": 1
      },
      "type": "image",
      "link": "https://www.instagram.com/p/BqAwXhzlnol/",
      "location": {
        "latitude": 41.4099,
        "longitude": 2.1907,
        "name": "El Clot, Cataluna, Spain",
        "id": 253258441
      },
      "attribution": null,
      "users_in_photo": []
    },
    {
      "id": "1909643256872150488_31044967",
      "user": {
        "id": "31044967",
        "full_name": "Ramon",
        "profile_picture": "https://scontent.cdninstagram.com/vp/67c443456e0b9a1e8c4e86177a82ee67/5CDE2DBC/t51.2885-19/s150x150/25038116_1902832036711656_8761951227660468224_n.jpg?_nc_ht=scontent.cdninstagram.com",
        "username": "freecates"
      },
      "images": {
        "thumbnail": {
          "width": 150,
          "height": 150,
          "url": "https://scontent.cdninstagram.com/vp/41c9f902aec76ecf796de443a18f1f01/5CBB067F/t51.2885-15/e35/s150x150/42394448_563648774064206_4557058586005427970_n.jpg?_nc_ht=scontent.cdninstagram.com"
        },
        "low_resolution": {
          "width": 320,
          "height": 320,
          "url": "https://scontent.cdninstagram.com/vp/f6e7e8097efedc55f370ca206ba13053/5CDCF48F/t51.2885-15/e35/s320x320/42394448_563648774064206_4557058586005427970_n.jpg?_nc_ht=scontent.cdninstagram.com"
        },
        "standard_resolution": {
          "width": 640,
          "height": 640,
          "url": "https://scontent.cdninstagram.com/vp/2c480d89ae58b465e3c52d7a99085f88/5CDD39D8/t51.2885-15/sh0.08/e35/s640x640/42394448_563648774064206_4557058586005427970_n.jpg?_nc_ht=scontent.cdninstagram.com"
        }
      },
      "created_time": "1541867237",
      "caption": {
        "id": "17968964815178430",
        "text": "Per mots anys @budhha_10__ !",
        "created_time": "1541867237",
        "from": {
          "id": "31044967",
          "full_name": "Ramon",
          "profile_picture": "https://scontent.cdninstagram.com/vp/67c443456e0b9a1e8c4e86177a82ee67/5CDE2DBC/t51.2885-19/s150x150/25038116_1902832036711656_8761951227660468224_n.jpg?_nc_ht=scontent.cdninstagram.com",
          "username": "freecates"
        }
      },
      "user_has_liked": true,
      "likes": {
        "count": 8
      },
      "tags": [],
      "filter": "Clarendon",
      "comments": {
        "count": 0
      },
      "type": "image",
      "link": "https://www.instagram.com/p/BqAamyllaXY/",
      "location": {
        "latitude": 41.39587,
        "longitude": 1.95917,
        "name": "Cervelló",
        "id": 1696908447214325
      },
      "attribution": null,
      "users_in_photo": []
    }
  ],
  "meta": {
    "code": 200
  }
}
